fracdiff2/__init__.py
fracdiff2/fracdiff.py
fracdiff2-1.1.dist-info/LICENSE
fracdiff2-1.1.dist-info/METADATA
fracdiff2-1.1.dist-info/WHEEL
fracdiff2-1.1.dist-info/top_level.txt
fracdiff2-1.1.dist-info/RECORD
